LICENSE
MANIFEST.in
README.mkd
setup.py
django_mobler.egg-info/PKG-INFO
django_mobler.egg-info/SOURCES.txt
django_mobler.egg-info/dependency_links.txt
django_mobler.egg-info/not-zip-safe
django_mobler.egg-info/top_level.txt
mobler/__init__.py
mobler/browscap.py
mobler/middleware.py
mobler/models.py
mobler/settings.py
mobler/tests.py
mobler/views.py
mobler/templatetags/__init__.py
mobler/templatetags/mobler_tags.py