Metadata-Version: 1.0
Name: django-mobler
Version: 1.1.0
Summary: User-Agent-based mobile device detection for Django
Home-page: https://github.com/dmpayton/django-mobler
Author: Derek Payton
Author-email: derek.payton@gmail.com
License: MIT License
Download-URL: https://github.com/dmpayton/django-mobler/tarball/v1.1.0
Keywords: django mobile browscap
Platform: UNKNOWN
Classifier: Development Status :: 5 - Production/Stable
Classifier: Framework :: Django
Classifier: Intended Audience :: Developers
Classifier: License :: OSI Approved :: MIT License
Classifier: Natural Language :: English
Classifier: Operating System :: OS Independent
Classifier: Programming Language :: Python
Classifier: Topic :: Internet :: WWW/HTTP :: Dynamic Content
